lingxi_mlkit/__init__.py
lingxi_mlkit/config.py
lingxi_mlkit/dataset.py
lingxi_mlkit/model.py
lingxi_mlkit/train.py
lingxi_mlkit/util/__init__.py
lingxi_mlkit/util/data_handle/__init__.py
lingxi_mlkit/util/data_handle/time_series.py
lingxi_mlkit-0.0.2.dist-info/licenses/LICENSE
lingxi_mlkit-0.0.2.dist-info/METADATA
lingxi_mlkit-0.0.2.dist-info/WHEEL
lingxi_mlkit-0.0.2.dist-info/top_level.txt
lingxi_mlkit-0.0.2.dist-info/RECORD
