Metadata-Version: 2.4
Name: lingxi-mlkit
Version: 0.0.2
Summary: A Personal ML Kit package for Torch and Sklearn
Author-email: Lingxi <clodlingxi233@gmail.com>
License: MIT
Project-URL: Homepage, https://github.com/ClodLingxi/Lingxi-Mlkit
Project-URL: Repository, https://github.com/ClodLingxi/Lingxi-Mlkit
Classifier: Programming Language :: Python :: 3
Classifier: License :: OSI Approved :: MIT License
Classifier: Operating System :: OS Independent
Requires-Python: >=3.11
License-File: LICENSE
Requires-Dist: torch
Requires-Dist: scikit-learn
Requires-Dist: tqdm
Requires-Dist: swanlab
Requires-Dist: pandas
Dynamic: license-file
